Metadata-Version: 2.1
Name: fishhook-extended
Version: 0.0.1
Summary: Extended: Allows for runtime hooking of static class functions AND other type slots
Home-page: https://github.com/thatbirdguythatuknownot/fishhook-extended
Author: Crowthebird
Author-email: nohackingofkrowten@gmail.com
License: UNKNOWN
Platform: UNKNOWN
Classifier: Programming Language :: Python :: 3
Classifier: License :: OSI Approved :: MIT License
License-File: LICENSE
